jinja2ssg/__main__.py
jinja2ssg/builder.py
jinja2ssg-0.2.0.dist-info/METADATA
jinja2ssg-0.2.0.dist-info/WHEEL
jinja2ssg-0.2.0.dist-info/RECORD
