Metadata-Version: 2.1
Name: jinja2ssg
Version: 0.2.0
Summary: 
License: MIT
Author: Arjoonn Sharma
Author-email: arjoonn@midpathsoftware.com
Requires-Python: >=3.11,<4.0
Classifier: License :: OSI Approved :: MIT License
Classifier: Programming Language :: Python :: 3
Classifier: Programming Language :: Python :: 3.11
Classifier: Programming Language :: Python :: 3.12
Requires-Dist: click (>=8.1.7,<9.0.0)
Requires-Dist: jinja2 (>=3.1.2,<4.0.0)
Requires-Dist: pyyaml (>=6.0.1,<7.0.0)
Requires-Dist: watchdog (>=3.0.0,<4.0.0)
